Mensajes/__init__.py
Mensajes/Adios/__init__.py
Mensajes/Adios/despedida.py
Mensajes/hola/__init__.py
Mensajes/hola/saludos.py
test/__init__.py
test/test_hola.py
Mensajes_AntonioY92-1.6.dist-info/LICENSE
Mensajes_AntonioY92-1.6.dist-info/METADATA
Mensajes_AntonioY92-1.6.dist-info/WHEEL
Mensajes_AntonioY92-1.6.dist-info/top_level.txt
Mensajes_AntonioY92-1.6.dist-info/RECORD
