Metadata-Version: 2.1
Name: Mensajes-AntonioY92
Version: 1.6
Summary: Un paquete para saludar
Home-page: 
Author: AntonioY92
Author-email: correo@gmail.com
Classifier: Environment :: Console
Classifier: Intended Audience :: Developers
Classifier: Topic :: Utilities
License-File: LICENSE
Requires-Dist: numpy (==1.24.0)
